friday/__init__.py
friday/api/__init__.py
friday/api/app.py
friday/api/middleware.py
friday/api/routes/__init__.py
friday/api/routes/crawl.py
friday/api/routes/generate.py
friday/api/routes/health.py
friday/api/routes/version.py
friday/api/schemas/__inti__.py
friday/api/schemas/crawl.py
friday/api/schemas/generate.py
friday/api/schemas/version.py
friday/cli.py
friday/config/__init__.py
friday/config/config.py
friday/connectors/__init__.py
friday/connectors/confluence_client.py
friday/connectors/github_client.py
friday/connectors/jira_client.py
friday/models/__init__.py
friday/models/test_case.py
friday/services/__init__.py
friday/services/crawler.py
friday/services/embeddings.py
friday/services/test_generator.py
friday/utils/__init__.py
friday/utils/helpers.py
friday/version.py
friday_cli-0.1.45.dist-info/LICENSE
friday_cli-0.1.45.dist-info/METADATA
friday_cli-0.1.45.dist-info/WHEEL
friday_cli-0.1.45.dist-info/entry_points.txt
friday_cli-0.1.45.dist-info/RECORD
