Metadata-Version: 2.3
Name: friday-cli
Version: 0.1.45
Summary: AI-powered test case generator CLI
License: MIT
Keywords: atlassian,jira,google,github,vertexai,genai,chroma,openai,deepseek,cli
Author: Dipjyoti Metia
Author-email: dipjyotimetia@gmail.com
Requires-Python: >=3.12,<4.0
Classifier: Development Status :: 4 - Beta
Classifier: Environment :: Console
Classifier: Intended Audience :: Developers
Classifier: License :: OSI Approved :: MIT License
Classifier: Operating System :: OS Independent
Classifier: Programming Language :: Python :: 3
Classifier: Programming Language :: Python :: 3.12
Classifier: Programming Language :: Python :: 3.13
Classifier: Topic :: Software Development :: Quality Assurance
Classifier: Topic :: Software Development :: Testing
Requires-Dist: atlassian-python-api (>=3.41.19,<4.0.0)
Requires-Dist: chromadb (>=0.5.23,<0.6.0)
Requires-Dist: fastapi (>=0.115.7,<0.116.0)
Requires-Dist: google-cloud-aiplatform (>=1.79.0,<2.0.0)
Requires-Dist: google-genai (>=0.7.0,<0.8.0)
Requires-Dist: langchain (>=0.3.16,<0.4.0)
Requires-Dist: langchain-chroma (>=0.2.1,<0.3.0)
Requires-Dist: langchain-community (>=0.3.16,<0.4.0)
Requires-Dist: langchain-core (>=0.3.32,<0.4.0)
Requires-Dist: langchain-deepseek (>=0.0.1,<0.0.2)
Requires-Dist: langchain-google-genai (>=2.0.9,<3.0.0)
Requires-Dist: langchain-google-vertexai (>=2.0.12,<3.0.0)
Requires-Dist: langchain-openai (>=0.3.2,<0.4.0)
Requires-Dist: pygithub (>=2.5.0,<3.0.0)
Requires-Dist: python-dotenv (>=1.0.1,<2.0.0)
Requires-Dist: python-json-logger (>=3.2.1,<4.0.0)
Requires-Dist: retrying (>=1.3.4,<2.0.0)
Requires-Dist: scrapy (>=2.12.0,<3.0.0)
Requires-Dist: typer (>=0.15.1,<0.16.0)
Requires-Dist: uvicorn[standard] (>=0.34.0,<0.35.0)
Project-URL: Bug Tracker, https://github.com/dipjyotimetia/friday/issues
Project-URL: Homepage, https://github.com/dipjyotimetia/friday
